{
  "_format": "hh-sol-cache-2",
  "files": {
    "C:\\Users\\Egemen\\Documents\\GitHub\\egepoly-hub\\contracts\\FootballData.sol": {
      "lastModificationDate": 1729207050217,
      "contentHash": "5bcea75d473e0af046603ead4fed650d",
      "sourceName": "contracts/FootballData.sol",
      "solcConfig": {
        "version": "0.8.26",
        "settings": {
          "evmVersion": "paris",
          "optimizer": {
            "enabled": false,
            "runs": 200
          },
          "outputSelection": {
            "*": {
              "*": [
                "abi",
                "evm.bytecode",
                "evm.deployedBytecode",
                "evm.methodIdentifiers",
                "metadata"
              ],
              "": [
                "ast"
              ]
            }
          }
        }
      },
      "imports": [],
      "versionPragmas": [
        "^0.8.26"
      ],
      "artifacts": [
        "FootballData"
      ]
    }
  }
}
